datamutant/__init__.py
datamutant/monotonicity_score/__init__.py
datamutant/monotonicity_score/models.py
datamutant/monotonicity_score/sublinear.py
datamutant/monotonicity_score/examples/__init__.py
datamutant/monotonicity_score/examples/basic_usage.py
datamutant/monotonicity_score/examples/model_training.py
datamutant-0.1.0.dist-info/licenses/LICENSE
tests/__init__.py
tests/monotonicity_score/__init__.py
tests/monotonicity_score/test_core.py
tests/monotonicity_score/test_models.py
datamutant-0.1.0.dist-info/METADATA
datamutant-0.1.0.dist-info/WHEEL
datamutant-0.1.0.dist-info/top_level.txt
datamutant-0.1.0.dist-info/RECORD
